examples/__init__.py
examples/client.py
examples/json_file_services.py
examples/mongodb_services.py
examples/redis_services.py
rtconfig/__init__.py
rtconfig/auth.py
rtconfig/backend.py
rtconfig/cli.py
rtconfig/client.py
rtconfig/exceptions.py
rtconfig/helpers.py
rtconfig/manager.py
rtconfig/message.py
rtconfig/mixin.py
rtconfig/server.py
rtconfig/utils.py
rtconfig/views.py
rtconfig/static/css/admin.css
rtconfig/static/css/global.css
rtconfig/static/css/layui.css
rtconfig/static/css/login.css
rtconfig/static/css/modules/layer/default/layer.css
rtconfig/static/font/iconfont.eot
rtconfig/static/font/iconfont.svg
rtconfig/static/font/iconfont.ttf
rtconfig/static/font/iconfont.woff
rtconfig/static/images/face/0.gif
rtconfig/static/images/face/1.gif
rtconfig/static/images/face/10.gif
rtconfig/static/images/face/11.gif
rtconfig/static/images/face/12.gif
rtconfig/static/images/face/13.gif
rtconfig/static/images/face/14.gif
rtconfig/static/images/face/15.gif
rtconfig/static/images/face/16.gif
rtconfig/static/images/face/17.gif
rtconfig/static/images/face/18.gif
rtconfig/static/images/face/19.gif
rtconfig/static/images/face/2.gif
rtconfig/static/images/face/20.gif
rtconfig/static/images/face/21.gif
rtconfig/static/images/face/22.gif
rtconfig/static/images/face/23.gif
rtconfig/static/images/face/24.gif
rtconfig/static/images/face/25.gif
rtconfig/static/images/face/26.gif
rtconfig/static/images/face/27.gif
rtconfig/static/images/face/28.gif
rtconfig/static/images/face/29.gif
rtconfig/static/images/face/3.gif
rtconfig/static/images/face/30.gif
rtconfig/static/images/face/31.gif
rtconfig/static/images/face/32.gif
rtconfig/static/images/face/33.gif
rtconfig/static/images/face/34.gif
rtconfig/static/images/face/35.gif
rtconfig/static/images/face/36.gif
rtconfig/static/images/face/37.gif
rtconfig/static/images/face/38.gif
rtconfig/static/images/face/39.gif
rtconfig/static/images/face/4.gif
rtconfig-0.1.8.dist-info/METADATA
rtconfig-0.1.8.dist-info/RECORD
rtconfig-0.1.8.dist-info/WHEEL
rtconfig-0.1.8.dist-info/top_level.txt
