Metadata-Version: 2.1
Name: rtconfig
Version: 0.1.8
Summary: A simple python real-time remote configuration framework.
Home-page: https://github.com/dwpy/rtconfig
Author: Dongwei
License: BSD
Project-URL: Code, https://github.com/dwpy/rtconfig
Platform: any
Classifier: Development Status :: 1 - Planning
Classifier: Environment :: Web Environment
Classifier: Intended Audience :: Developers
Classifier: License :: OSI Approved :: BSD License
Classifier: Operating System :: OS Independent
Classifier: Programming Language :: Python :: 3.5
Classifier: Programming Language :: Python :: 3.6
Classifier: Programming Language :: Python :: 3.7
Requires-Python: >=3.5
Requires-Dist: attrs
Requires-Dist: uwsgidecorators
Requires-Dist: python-dotenv
Requires-Dist: websockets (==6.0)
